Workbook

Sheet RESULTADO
D1: REALIZADO
A2: DISCRIMINAÇÃO | D2: VALOR R$
A3: 1.Faturamento YOU
A4: Reembolsos stone
A5: A&B&E | D5: =SUM('Faturamento L1 e L2'!J27:K27,'Faturamento L1 e L2'!M27,'Faturamento RTC'!J17:K17,'Faturamento RTC'!M17) -> 0
A7: 2.Faturamento Experience | D7: =SUM(D8:D9) -> 0
A8: L1 + L2 | D8: =SUM('Faturamento L1 e L2'!I27,'Faturamento L1 e L2'!L27) -> 0
A9: RTC | D9: =SUM('Faturamento RTC'!I17,'Faturamento RTC'!L17) -> 0
A10: Total
A12: 4. Custos Loja You | D12: VALOR R$
A13: Total | D13: ='GASTOS POR ESPAÇO'!B124 -> 116271.65
A14: Resultado You BAR | D14: =D3-D13 -> -116271.65
A17: 8. Espaços 178 | B17: Receitas | C17: Despesas | D17: Resultado
A18: L1 + L2 | B18: =D8 -> 0 | C18: =SUM('GASTOS POR ESPAÇO'!E124,'GASTOS POR ESPAÇO'!H124) -> 40406.124 | D18: =B18-C18 -> -40406.124
A19: RTC | B19: =D9 -> 0 | C19: ='GASTOS POR ESPAÇO'!K124 -> 7923.2951 | D19: =B19-C19 -> -7923.2951
A21: Resultado 178 | D21: =SUM(D18:D19) -> -48329.419
C22: Yield (3mi) | D22: =D21/3000000 -> -0.016109806
B28: 62311
B29: 29284
B31: =SUM(B28:B30) -> 91595 | C31: =SUM(C18:C19,D13) -> 164601.07
B32: 104000

Sheet Faturamento L1 e L2

Sheet Faturamento RTC
A1: Simulação | B1: Reserva | C1: Cliente | D1: Data Aceite | E1: Data Check-in | G1: Valor sim. | H1: Locação espaço | I1: Alim./bebidas | J1: Equipe apoio | K1: Loc. equip. | L1: Entretenimento | M1: Total | N1: Anúncio | O1: Tem Check-out?
A2: [7539] | B2: 4981 | C2: Elaine Maria Silva de Souza | D2: 46066 | E2: 46082 | F2: =G2-SUM(H2:L2) -> 900 | G2: 3000 | H2: 2100 | I2: 0 | J2: 0 | K2: 0 | L2: 0 | M2: 2100 | N2: 0 | O2: Sim
A3: [7213] | B3: 4925 | C3: Ana Beneck | D3: 46050 | E3: 46088 | F3: =G3-SUM(H3:L3) -> 1111.5 | G3: 3736.5 | H3: =G3-1111.5 -> 2625 | I3: 0 | J3: 0 | K3: 0 | L3: 0 | M3: 0 | N3: 146 | O3: SEM DESOCUP.
A4: [7601] | B4: 4994 | C4: Sharim Amar Borrione Arab | D4: 46073 | E4: 46089 | F4: =G4-SUM(H4:L4) -> 900 | G4: 3000 | H4: 2100 | I4: 0 | J4: 0 | K4: 0 | L4: 0 | M4: 2100 | N4: 64 | O4: Sim
A5: [7563] | B5: 4988 | C5: Globopack Embalagens | D5: 46071 | E5: 46091 | F5: =G5-SUM(H5:L5) -> 900 | G5: 3000 | H5: 2100 | I5: 0 | J5: 0 | K5: 0 | L5: 0 | M5: 2100 | N5: 121 | O5: Sim
A6: [7510] | B6: 4972 | C6: Juliana Maria Andrade de Carvalho | D6: 46065 | E6: 46092 | F6: =G6-SUM(H6:L6) -> 900 | G6: 3000 | H6: 2100 | I6: 0 | J6: 0 | K6: 0 | L6: 0 | M6: 2100 | N6: 0 | O6: Sim
A7: [7804] | B7: 5019 | C7: Maria Eduarda penkal | D7: 46091 | E7: 46093 | F7: =G7-SUM(H7:L7) -> 0 | G7: 200 | H7: 0 | I7: 0 | J7: 0 | K7: 200 | L7: 0 | M7: 200 | N7: 0 | O7: Sim
A8: [7731] | B8: 5010 | C8: Fabiola Gonçalves dos Santos | D8: 46084 | E8: 46095 | F8: =G8-SUM(H8:L8) -> 0 | G8: 165 | H8: 165 | I8: 0 | J8: 0 | K8: 0 | L8: 0 | M8: 165 | N8: 175 | O8: SEM DESOCUP.
A9: [6976] | B9: A confirmar | C9: Fabiola Gonçalves dos Santos | D9: 46034 | E9: 46095 | F9: =G9-SUM(H9:L9) -> 900 | G9: 900 | H9: 0 | I9: 0 | J9: 0 | K9: 0 | L9: 0 | M9: 0 | N9: 175 | O9: SEM DESOCUP.
A10: [6975] | B10: 4890 | C10: Fabiola Gonçalves dos Santos | D10: 46034 | E10: 46095 | F10: =G10-SUM(H10:L10) -> 157.5 | G10: 2782.5 | H10: 2625 | I10: 0 | J10: 0 | K10: 0 | L10: 0 | M10: 2625 | N10: 175 | O10: Sim
A11: [7900] | B11: 5028 | C11: Emanuel Ribas Santos | D11: 46098 | E11: 46098 | F11: =G11-SUM(H11:L11) -> 0 | G11: 278.1 | H11: 0 | I11: 278.1 | J11: 0 | K11: 0 | L11: 0 | M11: 278.1 | N11: 0 | O11: SEM DESOCUP.
A12: [6768] | B12: 4859 | C12: Cirde Eufrázio da Silva Filho | D12: 46010 | E12: 46102 | F12: =G12-SUM(H12:L12) -> 900 | G12: 3400 | H12: 2500 | I12: 0 | J12: 0 | K12: 0 | L12: 0 | M12: 2500 | N12: 0 | O12: Sim
A13: [7461] | B13: 4962 | C13: Thays cândido da silva | D13: 46063 | E13: 46109 | F13: =G13-SUM(H13:L13) -> 900 | G13: 3525 | H13: 2625 | I13: 0 | J13: 0 | K13: 0 | L13: 0 | M13: 2625 | N13: 0 | O13: Sim
H15: =SUM(H2:H13) -> 18940 | I15: =SUM(I2:I13) -> 278.1 | J15: =SUM(J2:J13) -> 0 | K15: =SUM(K2:K13) -> 200 | L15: =SUM(L2:L13) -> 0
E18: 178 | F18: =SUM(H15,K15) -> 19140

Sheet GASTOS POR ESPAÇO
A1: YOU | D1: L1 | G1: L2 | J1: RTC
A2: FORNECEDOR/GRUPO | B2: REALIZADO | D2: FORNECEDOR/GRUPO | E2: REALIZADO | G2: FORNECEDOR/GRUPO | H2: REALIZADO | J2: FORNECEDOR/GRUPO | K2: REALIZADO
A3: BAR | D3: BAR | G3: BAR | J3: BAR
A4: INSUMO BAR | B4: =SUMIFS('GASTOS DETALHADOS'!$C:$C,'GASTOS DETALHADOS'!$E:$E,A$1,'GASTOS DETALHADOS'!$F:$F,A4) -> 11786.73 | D4: INSUMO BAR | E4: =SUMIFS('GASTOS DETALHADOS'!$C:$C,'GASTOS DETALHADOS'!$E:$E,D$1,'GASTOS DETALHADOS'!$F:$F,D4) -> 0 | G4: INSUMO BAR | H4: =SUMIFS('GASTOS DETALHADOS'!$C:$C,'GASTOS DETALHADOS'!$E:$E,G$1,'GASTOS DETALHADOS'!$F:$F,G4) -> 0 | J4: INSUMO BAR | K4: =SUMIFS('GASTOS DETALHADOS'!$C:$C,'GASTOS DETALHADOS'!$E:$E,J$1,'GASTOS DETALHADOS'!$F:$F,J4) -> 0
A5: Utensílios | D5: Utensílios | G5: Utensílios | J5: Utensílios
B6: =SUM(B4:B5) -> 11786.73 | E6: =SUM(E4:E5) -> 0 | H6: =SUM(H4:H5) -> 0 | K6: =SUM(K4:K5) -> 0
A7: COZINHA | D7: COZINHA | G7: COZINHA | J7: COZINHA
A8: INSUMO COZ | B8: =SUMIFS('GASTOS DETALHADOS'!$C:$C,'GASTOS DETALHADOS'!$E:$E,A$1,'GASTOS DETALHADOS'!$F:$F,A8) -> 32088.31 | D8: INSUMO COZ | E8: =SUMIFS('GASTOS DETALHADOS'!$C:$C,'GASTOS DETALHADOS'!$E:$E,D$1,'GASTOS DETALHADOS'!$F:$F,D8) -> 0 | G8: INSUMO COZ | H8: =SUMIFS('GASTOS DETALHADOS'!$C:$C,'GASTOS DETALHADOS'!$E:$E,G$1,'GASTOS DETALHADOS'!$F:$F,G8) -> 0 | J8: INSUMO COZ | K8: =SUMIFS('GASTOS DETALHADOS'!$C:$C,'GASTOS DETALHADOS'!$E:$E,J$1,'GASTOS DETALHADOS'!$F:$F,J8) -> 0
A9: Utensílios | D9: Utensílios | G9: Utensílios | J9: Utensílios
B10: =SUM(B8:B9) -> 32088.31 | E10: =SUM(E8:E9) -> 0 | H10: =SUM(H8:H9) -> 0 | K10: =SUM(K8:K9) -> 0
A11: SALÃO | D11: SALÃO | G11: SALÃO | J11: SALÃO
A12: INSUMO SALÃO | B12: =SUMIFS('GASTOS DETALHADOS'!$C:$C,'GASTOS DETALHADOS'!$E:$E,A$1,'GASTOS DETALHADOS'!$F:$F,A12) -> 265.7 | D12: INSUMO SALÃO | E12: =SUMIFS('GASTOS DETALHADOS'!$C:$C,'GASTOS DETALHADOS'!$E:$E,D$1,'GASTOS DETALHADOS'!$F:$F,D12) -> 355.89 | G12: INSUMO SALÃO | H12: =SUMIFS('GASTOS DETALHADOS'!$C:$C,'GASTOS DETALHADOS'!$E:$E,G$1,'GASTOS DETALHADOS'!$F:$F,G12) -> 0 | J12: INSUMO SALÃO | K12: =SUMIFS('GASTOS DETALHADOS'!$C:$C,'GASTOS DETALHADOS'!$E:$E,J$1,'GASTOS DETALHADOS'!$F:$F,J12) -> 0
A13: ALUGUEL ITENS DIVERSOS | B13: =SUMIFS('GASTOS DETALHADOS'!$C:$C,'GASTOS DETALHADOS'!$E:$E,A$1,'GASTOS DETALHADOS'!$F:$F,A13) -> 3369 | D13: ALUGUEL ITENS DIVERSOS | E13: =SUMIFS('GASTOS DETALHADOS'!$C:$C,'GASTOS DETALHADOS'!$E:$E,D$1,'GASTOS DETALHADOS'!$F:$F,D13) -> 3210 | G13: ALUGUEL ITENS DIVERSOS | H13: =SUMIFS('GASTOS DETALHADOS'!$C:$C,'GASTOS DETALHADOS'!$E:$E,G$1,'GASTOS DETALHADOS'!$F:$F,G13) -> 0 | J13: ALUGUEL ITENS DIVERSOS | K13: =SUMIFS('GASTOS DETALHADOS'!$C:$C,'GASTOS DETALHADOS'!$E:$E,J$1,'GASTOS DETALHADOS'!$F:$F,J13) -> 0
A14: Utensílios | B14: =SUMIFS('GASTOS DETALHADOS'!$C:$C,'GASTOS DETALHADOS'!$E:$E,A$1,'GASTOS DETALHADOS'!$F:$F,A14) -> 0 | D14: Utensílios | E14: =SUMIFS('GASTOS DETALHADOS'!$C:$C,'GASTOS DETALHADOS'!$E:$E,D$1,'GASTOS DETALHADOS'!$F:$F,D14) -> 0 | G14: Utensílios | H14: =SUMIFS('GASTOS DETALHADOS'!$C:$C,'GASTOS DETALHADOS'!$E:$E,G$1,'GASTOS DETALHADOS'!$F:$F,G14) -> 0 | J14: Utensílios | K14: =SUMIFS('GASTOS DETALHADOS'!$C:$C,'GASTOS DETALHADOS'!$E:$E,J$1,'GASTOS DETALHADOS'!$F:$F,J14) -> 0
B15: =SUM(B12:B14) -> 3634.7 | E15: =SUM(E12:E14) -> 3565.89 | H15: =SUM(H12:H14) -> 0 | K15: =SUM(K12:K14) -> 0
A16: LIMPEZA | D16: LIMPEZA | G16: LIMPEZA | J16: LIMPEZA
A17: INSUMO LIMP | B17: =SUMIFS('GASTOS DETALHADOS'!$C:$C,'GASTOS DETALHADOS'!$E:$E,A$1,'GASTOS DETALHADOS'!$F:$F,A17) -> 19 | D17: INSUMO LIMP | E17: =SUMIFS('GASTOS DETALHADOS'!$C:$C,'GASTOS DETALHADOS'!$E:$E,D$1,'GASTOS DETALHADOS'!$F:$F,D17) -> 514.09333 | G17: INSUMO LIMP | H17: =SUMIFS('GASTOS DETALHADOS'!$C:$C,'GASTOS DETALHADOS'!$E:$E,G$1,'GASTOS DETALHADOS'!$F:$F,G17) -> 514.09333 | J17: INSUMO LIMP | K17: =SUMIFS('GASTOS DETALHADOS'!$C:$C,'GASTOS DETALHADOS'!$E:$E,J$1,'GASTOS DETALHADOS'!$F:$F,J17) -> 514.09333
A18: Utensílios | B18: =SUMIFS('GASTOS DETALHADOS'!$C:$C,'GASTOS DETALHADOS'!$E:$E,A$1,'GASTOS DETALHADOS'!$F:$F,A18) -> 0 | D18: Utensílios | E18: =SUMIFS('GASTOS DETALHADOS'!$C:$C,'GASTOS DETALHADOS'!$E:$E,D$1,'GASTOS DETALHADOS'!$F:$F,D18) -> 0 | G18: Utensílios | H18: =SUMIFS('GASTOS DETALHADOS'!$C:$C,'GASTOS DETALHADOS'!$E:$E,G$1,'GASTOS DETALHADOS'!$F:$F,G18) -> 0 | J18: Utensílios | K18: =SUMIFS('GASTOS DETALHADOS'!$C:$C,'GASTOS DETALHADOS'!$E:$E,J$1,'GASTOS DETALHADOS'!$F:$F,J18) -> 0
B19: =SUM(B17:B18) -> 19 | E19: =SUM(E17:E18) -> 514.09333 | H19: =SUM(H17:H18) -> 514.09333 | K19: =SUM(K17:K18) -> 514.09333
A20: PALCO | D20: PALCO | G20: PALCO | H20: =SUMIFS('GASTOS DETALHADOS'!$C:$C,'GASTOS DETALHADOS'!$E:$E,G$1,'GASTOS DETALHADOS'!$F:$F,G20) -> 0 | J20: PALCO
A21: Insumos | B21: =SUMIFS('GASTOS DETALHADOS'!$C:$C,'GASTOS DETALHADOS'!$E:$E,A$1,'GASTOS DETALHADOS'!$F:$F,A21) -> 0 | D21: Insumos | E21: =SUMIFS('GASTOS DETALHADOS'!$C:$C,'GASTOS DETALHADOS'!$E:$E,D$1,'GASTOS DETALHADOS'!$F:$F,D21) -> 0 | G21: Insumos | H21: =SUMIFS('GASTOS DETALHADOS'!$C:$C,'GASTOS DETALHADOS'!$E:$E,G$1,'GASTOS DETALHADOS'!$F:$F,G21) -> 0 | J21: Insumos | K21: =SUMIFS('GASTOS DETALHADOS'!$C:$C,'GASTOS DETALHADOS'!$E:$E,J$1,'GASTOS DETALHADOS'!$F:$F,J21) -> 0
A22: Utensílios | B22: =SUMIFS('GASTOS DETALHADOS'!$C:$C,'GASTOS DETALHADOS'!$E:$E,A$1,'GASTOS DETALHADOS'!$F:$F,A22) -> 0 | D22: Utensílios | E22: =SUMIFS('GASTOS DETALHADOS'!$C:$C,'GASTOS DETALHADOS'!$E:$E,D$1,'GASTOS DETALHADOS'!$F:$F,D22) -> 0 | G22: Utensílios | H22: =SUMIFS('GASTOS DETALHADOS'!$C:$C,'GASTOS DETALHADOS'!$E:$E,G$1,'GASTOS DETALHADOS'!$F:$F,G22) -> 0 | J22: Utensílios | K22: =SUMIFS('GASTOS DETALHADOS'!$C:$C,'GASTOS DETALHADOS'!$E:$E,J$1,'GASTOS DETALHADOS'!$F:$F,J22) -> 0
B23: =SUM(B21:B22) -> 0 | E23: =SUM(E21:E22) -> 0 | H23: =SUM(H21:H22) -> 0 | K23: =SUM(K21:K22) -> 0
A24: MANUTENÇÃO | D24: MANUTENÇÃO | G24: MANUTENÇÃO | J24: MANUTENÇÃO
A25: REPOSIÇÃO INSUMOS | B25: =SUMIFS('GASTOS DETALHADOS'!$C:$C,'GASTOS DETALHADOS'!$E:$E,A$1,'GASTOS DETALHADOS'!$F:$F,A25) -> 0 | D25: REPOSIÇÃO INSUMOS | E25: =SUMIFS('GASTOS DETALHADOS'!$C:$C,'GASTOS DETALHADOS'!$E:$E,D$1,'GASTOS DETALHADOS'!$F:$F,D25) -> 0 | G25: REPOSIÇÃO INSUMOS | H25: =SUMIFS('GASTOS DETALHADOS'!$C:$C,'GASTOS DETALHADOS'!$E:$E,G$1,'GASTOS DETALHADOS'!$F:$F,G25) -> 0 | J25: REPOSIÇÃO INSUMOS | K25: =SUMIFS('GASTOS DETALHADOS'!$C:$C,'GASTOS DETALHADOS'!$E:$E,J$1,'GASTOS DETALHADOS'!$F:$F,J25) -> 395
A26: MANUTENÇÃO | B26: =SUMIFS('GASTOS DETALHADOS'!$C:$C,'GASTOS DETALHADOS'!$E:$E,A$1,'GASTOS DETALHADOS'!$F:$F,A26) -> 650 | D26: MANUTENÇÃO | E26: =SUMIFS('GASTOS DETALHADOS'!$C:$C,'GASTOS DETALHADOS'!$E:$E,D$1,'GASTOS DETALHADOS'!$F:$F,D26) -> 515.3 | G26: MANUTENÇÃO | H26: =SUMIFS('GASTOS DETALHADOS'!$C:$C,'GASTOS DETALHADOS'!$E:$E,G$1,'GASTOS DETALHADOS'!$F:$F,G26) -> 0 | J26: MANUTENÇÃO | K26: =SUMIFS('GASTOS DETALHADOS'!$C:$C,'GASTOS DETALHADOS'!$E:$E,J$1,'GASTOS DETALHADOS'!$F:$F,J26) -> 0
B27: =SUM(B25:B26) -> 650 | E27: =SUM(E25:E26) -> 515.3 | H27: =SUM(H25:H26) -> 0 | K27: =SUM(K25:K26) -> 395
A28: DESPESAS FIXAS | D28: DESPESAS FIXAS | G28: DESPESAS FIXAS | J28: DESPESAS FIXAS
A29: PROLÁBORE | B29: 6546.3 | D29: ENERGIA | E29: 1500 | G29: ENERGIA | H29: 1000 | J29: ENERGIA | K29: 800
A30: ENERGIA | B30: 1500 | D30: IPTU | E30: 278 | G30: IPTU | H30: 278 | J30: IPTU | K30: 164
A31: CUSTOS BÁSICOS | B31: =SUMIFS('GASTOS DETALHADOS'!$C:$C,'GASTOS DETALHADOS'!$E:$E,A$1,'GASTOS DETALHADOS'!$F:$F,A31) -> 175.26 | D31: CUSTOS BÁSICOS | E31: =SUMIFS('GASTOS DETALHADOS'!$C:$C,'GASTOS DETALHADOS'!$E:$E,D$1,'GASTOS DETALHADOS'!$F:$F,D31) -> 0 | G31: CUSTOS BÁSICOS | H31: =SUMIFS('GASTOS DETALHADOS'!$C:$C,'GASTOS DETALHADOS'!$E:$E,G$1,'GASTOS DETALHADOS'!$F:$F,G31) -> 0 | J31: CUSTOS BÁSICOS | K31: =SUMIFS('GASTOS DETALHADOS'!$C:$C,'GASTOS DETALHADOS'!$E:$E,J$1,'GASTOS DETALHADOS'!$F:$F,J31) -> 0
B32: =SUM(B29:B31) -> 8221.56 | E32: =SUM(E29:E31) -> 1778 | H32: =SUM(H29:H31) -> 1278 | K32: =SUM(K29:K31) -> 964
A33: TRANSPORTE | B33: =SUMIFS('GASTOS DETALHADOS'!$C:$C,'GASTOS DETALHADOS'!$E:$E,A$1,'GASTOS DETALHADOS'!$F:$F,A33) -> 822.3 | D33: TRANSPORTE | E33: =SUMIFS('GASTOS DETALHADOS'!$C:$C,'GASTOS DETALHADOS'!$E:$E,D$1,'GASTOS DETALHADOS'!$F:$F,D33) -> 0 | G33: TRANSPORTE | H33: =SUMIFS('GASTOS DETALHADOS'!$C:$C,'GASTOS DETALHADOS'!$E:$E,G$1,'GASTOS DETALHADOS'!$F:$F,G33) -> 0 | J33: TRANSPORTE | K33: =SUMIFS('GASTOS DETALHADOS'!$C:$C,'GASTOS DETALHADOS'!$E:$E,J$1,'GASTOS DETALHADOS'!$F:$F,J33) -> 20.95
A34: UBER | B34: =SUMIFS('GASTOS DETALHADOS'!$C:$C,'GASTOS DETALHADOS'!$E:$E,A$1,'GASTOS DETALHADOS'!$F:$F,A34) -> 0 | D34: UBER | E34: =SUMIFS('GASTOS DETALHADOS'!$C:$C,'GASTOS DETALHADOS'!$E:$E,D$1,'GASTOS DETALHADOS'!$F:$F,D34) -> 0 | G34: UBER | H34: =SUMIFS('GASTOS DETALHADOS'!$C:$C,'GASTOS DETALHADOS'!$E:$E,G$1,'GASTOS DETALHADOS'!$F:$F,G34) -> 0 | J34: UBER | K34: =SUMIFS('GASTOS DETALHADOS'!$C:$C,'GASTOS DETALHADOS'!$E:$E,J$1,'GASTOS DETALHADOS'!$F:$F,J34) -> 0
A35: VALLET | B35: =SUMIFS('GASTOS DETALHADOS'!$C:$C,'GASTOS DETALHADOS'!$E:$E,A$1,'GASTOS DETALHADOS'!$F:$F,A35) -> 0 | D35: VALLET | E35: =SUMIFS('GASTOS DETALHADOS'!$C:$C,'GASTOS DETALHADOS'!$E:$E,D$1,'GASTOS DETALHADOS'!$F:$F,D35) -> 0 | G35: VALLET | H35: =SUMIFS('GASTOS DETALHADOS'!$C:$C,'GASTOS DETALHADOS'!$E:$E,G$1,'GASTOS DETALHADOS'!$F:$F,G35) -> 0 | J35: VALLET | K35: =SUMIFS('GASTOS DETALHADOS'!$C:$C,'GASTOS DETALHADOS'!$E:$E,J$1,'GASTOS DETALHADOS'!$F:$F,J35) -> 0
B36: =SUM(B34) -> 0 | E36: =SUM(E34) -> 0 | H36: =SUM(H34) -> 0 | K36: =SUM(K34) -> 0
A37: SISTEMA GESTÃO E VENDAS | D37: SISTEMA GESTÃO E VENDAS | E37: =SUMIFS('GASTOS DETALHADOS'!$C:$C,'GASTOS DETALHADOS'!$E:$E,D$1,'GASTOS DETALHADOS'!$F:$F,D37) -> 0 | G37: SISTEMA GESTÃO E VENDAS | H37: =SUMIFS('GASTOS DETALHADOS'!$C:$C,'GASTOS DETALHADOS'!$E:$E,G$1,'GASTOS DETALHADOS'!$F:$F,G37) -> 0 | J37: SISTEMA GESTÃO E VENDAS | K37: =SUMIFS('GASTOS DETALHADOS'!$C:$C,'GASTOS DETALHADOS'!$E:$E,J$1,'GASTOS DETALHADOS'!$F:$F,J37) -> 0
A38: SISTEMA | B38: =SUMIFS('GASTOS DETALHADOS'!$C:$C,'GASTOS DETALHADOS'!$E:$E,A$1,'GASTOS DETALHADOS'!$F:$F,A38) -> 0 | D38: SISTEMA | E38: =SUMIFS('GASTOS DETALHADOS'!$C:$C,'GASTOS DETALHADOS'!$E:$E,D$1,'GASTOS DETALHADOS'!$F:$F,D38) -> 52.8 | G38: SISTEMA | H38: =SUMIFS('GASTOS DETALHADOS'!$C:$C,'GASTOS DETALHADOS'!$E:$E,G$1,'GASTOS DETALHADOS'!$F:$F,G38) -> 47.8 | J38: SISTEMA | K38: =SUMIFS('GASTOS DETALHADOS'!$C:$C,'GASTOS DETALHADOS'!$E:$E,J$1,'GASTOS DETALHADOS'!$F:$F,J38) -> 0
B39: =B38 -> 0 | E39: =E38 -> 52.8 | H39: =H38 -> 47.8 | K39: =K38 -> 0
A40: MUSICOS | D40: MUSICOS | E40: =SUMIFS('GASTOS DETALHADOS'!$C:$C,'GASTOS DETALHADOS'!$E:$E,D$1,'GASTOS DETALHADOS'!$F:$F,D40) -> 0 | G40: MUSICOS | H40: =SUMIFS('GASTOS DETALHADOS'!$C:$C,'GASTOS DETALHADOS'!$E:$E,G$1,'GASTOS DETALHADOS'!$F:$F,G40) -> 0 | J40: MUSICOS | K40: =SUMIFS('GASTOS DETALHADOS'!$C:$C,'GASTOS DETALHADOS'!$E:$E,J$1,'GASTOS DETALHADOS'!$F:$F,J40) -> 0
A41: MÚSICOS | B41: =SUMIFS('GASTOS DETALHADOS'!$C:$C,'GASTOS DETALHADOS'!$E:$E,A$1,'GASTOS DETALHADOS'!$F:$F,A41) -> 552.5 | D41: MÚSICOS | E41: =SUMIFS('GASTOS DETALHADOS'!$C:$C,'GASTOS DETALHADOS'!$E:$E,D$1,'GASTOS DETALHADOS'!$F:$F,D41) -> 0 | G41: MÚSICOS | H41: =SUMIFS('GASTOS DETALHADOS'!$C:$C,'GASTOS DETALHADOS'!$E:$E,G$1,'GASTOS DETALHADOS'!$F:$F,G41) -> 0 | J41: MÚSICOS | K41: =SUMIFS('GASTOS DETALHADOS'!$C:$C,'GASTOS DETALHADOS'!$E:$E,J$1,'GASTOS DETALHADOS'!$F:$F,J41) -> 0
A42: SERVIÇO ADICIONAL CLIENTE | B42: =SUMIFS('GASTOS DETALHADOS'!$C:$C,'GASTOS DETALHADOS'!$E:$E,A$1,'GASTOS DETALHADOS'!$F:$F,A42) -> 0 | D42: SERVIÇO ADICIONAL CLIENTE | E42: =SUMIFS('GASTOS DETALHADOS'!$C:$C,'GASTOS DETALHADOS'!$E:$E,D$1,'GASTOS DETALHADOS'!$F:$F,D42) -> 0 | G42: SERVIÇO ADICIONAL CLIENTE | H42: =SUMIFS('GASTOS DETALHADOS'!$C:$C,'GASTOS DETALHADOS'!$E:$E,G$1,'GASTOS DETALHADOS'!$F:$F,G42) -> 0 | J42: SERVIÇO ADICIONAL CLIENTE | K42: =SUMIFS('GASTOS DETALHADOS'!$C:$C,'GASTOS DETALHADOS'!$E:$E,J$1,'GASTOS DETALHADOS'!$F:$F,J42) -> 0
A43: REEMBOLSO CLIENTE | B43: =SUMIFS('GASTOS DETALHADOS'!$C:$C,'GASTOS DETALHADOS'!$E:$E,A$1,'GASTOS DETALHADOS'!$F:$F,A43) -> 0 | D43: REEMBOLSO CLIENTE | E43: =SUMIFS('GASTOS DETALHADOS'!$C:$C,'GASTOS DETALHADOS'!$E:$E,D$1,'GASTOS DETALHADOS'!$F:$F,D43) -> 0 | G43: REEMBOLSO CLIENTE | H43: =SUMIFS('GASTOS DETALHADOS'!$C:$C,'GASTOS DETALHADOS'!$E:$E,G$1,'GASTOS DETALHADOS'!$F:$F,G43) -> 0 | J43: REEMBOLSO CLIENTE | K43: =SUMIFS('GASTOS DETALHADOS'!$C:$C,'GASTOS DETALHADOS'!$E:$E,J$1,'GASTOS DETALHADOS'!$F:$F,J43) -> 990
B44: =SUM(B41:B43) -> 552.5 | E44: =SUM(E41:E43) -> 0 | H44: =SUM(H41:H43) -> 0 | K44: =SUM(K41:K43) -> 990
A45: MARKETING | B45: =SUMIFS('GASTOS DETALHADOS'!$C:$C,'GASTOS DETALHADOS'!$E:$E,A$1,'GASTOS DETALHADOS'!$F:$F,A45) -> 4396.89 | D45: MARKETING | E45: =SUMIFS('GASTOS DETALHADOS'!$C:$C,'GASTOS DETALHADOS'!$E:$E,D$1,'GASTOS DETALHADOS'!$F:$F,D45) -> 4194.74 | G45: MARKETING | H45: =SUMIFS('GASTOS DETALHADOS'!$C:$C,'GASTOS DETALHADOS'!$E:$E,G$1,'GASTOS DETALHADOS'!$F:$F,G45) -> 3522.74 | J45: MARKETING | K45: =SUMIFS('GASTOS DETALHADOS'!$C:$C,'GASTOS DETALHADOS'!$E:$E,J$1,'GASTOS DETALHADOS'!$F:$F,J45) -> 2216.82
A46: Publicidade e Propaganda | B46: =SUMIFS('GASTOS DETALHADOS'!$C:$C,'GASTOS DETALHADOS'!$E:$E,A$1,'GASTOS DETALHADOS'!$F:$F,A46) -> 0 | D46: Publicidade e Propaganda | E46: =SUMIFS('GASTOS DETALHADOS'!$C:$C,'GASTOS DETALHADOS'!$E:$E,D$1,'GASTOS DETALHADOS'!$F:$F,D46) -> 0 | G46: Publicidade e Propaganda | H46: =SUMIFS('GASTOS DETALHADOS'!$C:$C,'GASTOS DETALHADOS'!$E:$E,G$1,'GASTOS DETALHADOS'!$F:$F,G46) -> 0 | J46: Publicidade e Propaganda | K46: =SUMIFS('GASTOS DETALHADOS'!$C:$C,'GASTOS DETALHADOS'!$E:$E,J$1,'GASTOS DETALHADOS'!$F:$F,J46) -> 0
B47: =SUM(B45:B46) -> 4396.89 | E47: =SUM(E45:E46) -> 4194.74 | H47: =SUM(H45:H46) -> 3522.74 | K47: =SUM(K45:K46) -> 2216.82
A48: STAFF | D48: STAFF | G48: STAFF | J48: STAFF
A49: Funcionarios CLT | B49: =SUM(B67,B50,B83) -> 7313.9236 | D49: Funcionario CLT | E49: =SUM(E67,E50,E83) -> 4389.5272 | G49: Funcionario CLT | H49: =SUM(H67,H50,H83) -> 3292.1454 | J49: Funcionario CLT | K49: =SUM(K67,K50,K83) -> 1097.3818
A50: Larissa Ghellere (20%) | B50: =SUM($E$66)*0.2 -> 1370.9316 | D50: Larissa Ghellere (40%) | E50: =SUM($E$66)*0.4 -> 2741.8632 | G50: Larissa Ghellere (30%) | H50: =E66*0.3 -> 2056.3974 | J50: Larissa Ghellere (10%) | K50: =E66*0.1 -> 685.4658
A51: 20% do total que está no L1 | D51: Salário Base | E51: 3510.05 | G51: 30% do total que está no L1 | J51: 10% do total que está no L1
D52: FGTS | E52: 393.12
D53: Multa Rescisória FGTS | E53: =40%*E52 -> 157.248
D54: Provisão FGTS sob ferias e 13 | E54: 31.2
D55: IR | E55: 0
D56: INSS | E56: 489.47
D57: Provisão INSS sob ferias e 13 | E57: 78
D58: Provisão 13 salario | E58: 292.5
D59: Provisão 1/3 Férias | E59: 97.5
D60: Adicional Noturno | E60: 0
D61: Adicional Cargo de Confiança | E61: =SUM(E51*0.4) -> 1404.02
D62: Bonificação | E62: 0
D63: Vale transporte | E63: 264
D64: Vale Alimentaçao | E64: 145
D65: Vale Refeição | E65: 482.02
D66: Total | E66: =SUM(E51,E53,E54,E52,E57,E58,E59,E61,E63,E64,E65) -> 6854.658
A67: Emanuel Ribas dos Santos | B67: =SUM(B68,B70,B71,B74,B69,B75,B76,B77,B78,B80,B81,B82,B79) -> 5119.16
A68: Salário Base | B68: 1900 | G68: Salário Base | H68: 3510.05 | J68: Salário Base | K68: 3510.05
A69: FGTS | B69: 212.8 | G69: FGTS | H69: 280.8 | J69: FGTS | K69: 280.8
A70: Multa Rescisória FGTS | B70: =40%*B69 -> 85.12 | G70: Multa Rescisória FGTS | H70: =40%*H69 -> 112.32 | J70: Multa Rescisória FGTS | K70: =40%*K69 -> 112.32
A71: Provisão FGTS sob ferias e 13 | B71: 16.89 | G71: Provisão FGTS sob ferias e 13 | H71: 31.2 | J71: Provisão FGTS sob ferias e 13 | K71: 31.2
A72: IR | B72: 0 | G72: IR | H72: 275.57 | J72: IR | K72: 275.57
A73: INSS | B73: 215.08 | G73: INSS | H73: 497.55 | J73: INSS | K73: 497.55
A74: Provisão INSS sob ferias e 13 | B74: 42.22 | G74: Provisão INSS sob ferias e 13 | H74: 78 | J74: Provisão INSS sob ferias e 13 | K74: 78
A75: Provisão 13 salario | B75: 158.33 | G75: Provisão 13 salario | H75: 292.5 | J75: Provisão 13 salario | K75: 292.5
A76: Provisão 1/3 Férias | B76: 52.78 | G76: Provisão 1/3 Férias | H76: 97.5 | J76: Provisão 1/3 Férias | K76: 97.5
A77: Adicional Noturno | B77: 0 | G77: Adicional Noturno | H77: 0 | J77: Adicional Noturno | K77: 0
A78: Adicional Cargo de Confiança | B78: =40%*B68 -> 760 | G78: Adicional Cargo de Confiança | H78: =SUM(H68*0.4) -> 1404.02 | J78: Adicional Cargo de Confiança | K78: =SUM(K68*0.4) -> 1404.02
A79: Bonificação | B79: 1000 | G79: Bonificação | H79: 0 | J79: Bonificação | K79: 0
A80: Vale transporte | B80: 264 | G80: Vale transporte | H80: =(12*23) -> 276 | J80: Vale transporte | K80: =(12*23) -> 276
A81: Vale Alimentaçao | B81: 145 | G81: Vale Alimentaçao | H81: 145 | J81: Vale Alimentaçao | K81: 145
A82: Vale Refeição | B82: 482.02 | G82: Vale Refeição | H82: =21.91*23 -> 503.93 | J82: Vale Refeição | K82: =21.91*23 -> 503.93
A83: Gabrielle de Fatima Ribeiro Cubas (20%) | B83: =SUM($E$99)*0.2 -> 823.832 | D83: Gabrielle de Fatima Ribeiro Cubas (40%) | E83: =E99*0.4 -> 1647.664 | G83: Gabrielle de Fatima Ribeiro Cubas (30%) | H83: =E99*0.3 -> 1235.748 | J83: Gabrielle de Fatima Ribeiro Cubas (10%) | K83: =SUM($E$99)*0.1 -> 411.916
A84: 20% do total que está no L1 | D84: Salário Base | E84: 1900 | G84: 30% do total que está no L1 | J84: 10% do total que está no L1
D85: FGTS | E85: 212.8
D86: Multa Rescisória FGTS | E86: 85.12
D87: Provisão FGTS sob ferias e 13 | E87: 16.89
D88: IR | E88: 0
D89: INSS | E89: 215.08
D90: Provisão INSS sob ferias e 13 | E90: 42.22
D91: Provisão 13 salario | E91: 158.33
D92: Provisão 1/3 Férias | E92: 52.78
D93: Adicional Noturno | E93: 0
D94: Adicional Cargo de Confiança | E94: =40%*E84 -> 760
D95: Bonificação | E95: 0
D96: Vale transporte | E96: 264
D97: Vale Alimentaçao | E97: 145
D98: Vale Refeição | E98: 482.02
D99: Total | E99: =SUM(E84,E85,E86,E87,E90,E91,E92,E94,E96,E97,E98) -> 4119.16
A100: NUTRICIONISTA | B100: 0
...

Sheet GASTOS DETALHADOS
A1: PI | B1: Dt. Pagto | C1: Vlr. Pagto | D1: Fornecedor | E1: ESPAÇO | F1: SETOR | G1: NF
A2: 178 | B2: 46143 | C2: 210 | D2: GREGORY GASPAR DE F. PROAK | E2: L1 | F2: SEGURANÇA | G2: 106
A3: 178 | B3: 46143 | C3: 100 | D3: Jordana Gabriela do Sanros Carvalho | E3: L1 | F3: STAFF FAXINA/MONTAGEM | G3: 107
A4: 176 | B4: 46147 | C4: 380 | D4: RAMALHETE DE MIRRA LOCACOES | E4: YOU | F4: ALUGUEL ITENS DIVERSOS | G4: 04052026
A5: 176 | B5: 46162 | C5: 1950 | D5: RAMALHETE DE MIRRA LOCACOES | E5: YOU | F5: ALUGUEL ITENS DIVERSOS | G5: 19052026
A6: 176 | B6: 46148 | C6: 585 | D6: VIP Service Personal Locação e Festas Ltda | E6: YOU | F6: ALUGUEL ITENS DIVERSOS | G6: 05052026
A7: 176 | B7: 46151 | C7: 42 | D7: VIP Service Personal Locação e Festas Ltda | E7: YOU | F7: ALUGUEL ITENS DIVERSOS | G7: reposicao coposalugados
A8: 176 | B8: 46151 | C8: 42 | D8: VIP Service Personal Locação e Festas Ltda | E8: YOU | F8: ALUGUEL ITENS DIVERSOS | G8: reposicao coposalugados
A9: 176 | B9: 46160 | C9: 370 | D9: VIP Service Personal Locação e Festas Ltda | E9: YOU | F9: ALUGUEL ITENS DIVERSOS | G9: 1805
A10: 176 | B10: 46160 | C10: 175.26 | D10: COPEL DISTRIBUICAO S/A | E10: YOU | F10: CUSTOS BÁSICOS | G10: 06052026146982
A11: 176 | B11: 46168 | C11: 113.27 | D11: Governo Federal / Imp. Ret. Forn / INSS | E11: YOU | F11: IMPOSTOS | G11: 2605
A12: 176 | B12: 46168 | C12: 113.27 | D12: Governo Federal / Imp. Ret. Forn / IR | E12: YOU | F12: IMPOSTOS | G12: 2605
A13: 176 | B13: 46149 | C13: 3341.64 | D13: Governo Federal / Imp. Ret. Forn / PIS-Coﬁns-CSLL | E13: YOU | F13: IMPOSTOS | G13: simples nacional
A14: 176 | B14: 46149 | C14: 9679.96 | D14: Governo Federal / Imp. Ret. Forn / PIS-Coﬁns-CSLL | E14: YOU | F14: IMPOSTOS | G14: simples nacional 2
A15: 176 | B15: 46168 | C15: 113.27 | D15: Governo Federal / Imp. Ret. Forn / PIS-Coﬁns-CSLL | E15: YOU | F15: IMPOSTOS | G15: 2605
... A34: 178 | B34: 46146 | C34: 19.4 | D34: 99 POP | E34: YOU | F34: TRANSPORTE | G34: manutencao maquina de
A35: 178 | B35: 46146 | C35: 120 | D35: ADRIEL DE OLIVEIRA FERNANDES | E35: L2 | F35: STAFF FAXINA/MONTAGEM | G35: 416
A36: 176 | B36: 46143 | C36: 2000 | D36: AÇOUGUE TIROLEZA | E36: YOU | F36: INSUMO COZ | G36: carnes 01 e 02
A37: 176 | B37: 46144 | C37: 69.86 | D37: AÇOUGUE TIROLEZA | E37: YOU | F37: INSUMO COZ | G37: carn3s 02/05
A38: 178 | B38: 46146 | C38: 109.4 | D38: EBAZAR.COM.BR LTDA | E38: L1 | F38: MANUTENÇÃO | G38: refil etiqueta
A39: 176 | B39: 46144 | C39: 225.41 | D39: AÇOUGUE TIROLEZA | E39: YOU | F39: INSUMO COZ | G39: estrogonoff staffcontratado
A40: 178 | B40: 46146 | C40: 1340 | D40: MADERA LOCACAO DE MOVEIS | E40: L1 | F40: ALUGUEL ITENS DIVERSOS | G40: 405
A41: 178 | B41: 46146 | C41: 195 | D41: Xin Eletronicos | E41: L1 | F41: MANUTENÇÃO | G41: 405
A42: 176 | B42: 46149 | C42: 1595.2 | D42: AÇOUGUE TIROLEZA | E42: YOU | F42: INSUMO COZ | G42: moida empanada,frango teriakymusculo ragu
A43: 176 | B43: 46154 | C43: 1112.15 | D43: AÇOUGUE TIROLEZA | E43: YOU | F43: INSUMO COZ | G43: eventos 08 e 09mini burguer,borghignon,mignon e
A44: 176 | B44: 46156 | C44: 252.92 | D44: AÇOUGUE TIROLEZA | E44: YOU | F44: INSUMO COZ | G44: mini burguer eteriaky
A45: 176 | B45: 46157 | C45: 179.74 | D45: AÇOUGUE TIROLEZA | E45: YOU | F45: INSUMO COZ | G45: musculobourghignon
A46: 176 | B46: 46163 | C46: 673.67 | D46: AÇOUGUE TIROLEZA | E46: YOU | F46: INSUMO COZ | G46: teriaky e ragu
A47: 176 | B47: 46170 | C47: 232.91 | D47: AÇOUGUE TIROLEZA | E47: YOU | F47: INSUMO COZ | G47: teriaky estrogonoff pacotestaff
A48: 176 | B48: 46147 | C48: 49.8 | D48: ARMAZEM DAS EMBALAGENS | E48: YOU | F48: INSUMO COZ | G48: caixinhas
A49: 176 | B49: 46151 | C49: 9.2 | D49: ARMAZEM DAS EMBALAGENS | E49: YOU | F49: INSUMO COZ | G49: embalagenshotdog
A50: 176 | B50: 46162 | C50: 53.6 | D50: ARMAZEM DAS EMBALAGENS | E50: YOU | F50: INSUMO COZ | G50: csixinhas
A51: 176 | B51: 46164 | C51: 78 | D51: ARMAZEM DAS EMBALAGENS | E51: YOU | F51: INSUMO COZ | G51: embalagempizzas
A52: 176 | B52: 46171 | C52: 52 | D52: ARMAZEM DAS EMBALAGENS | E52: YOU | F52: INSUMO COZ | G52: embalagens pizza
A53: 176 | B53: 46159 | C53: 26.16 | D53: Atacadao S A | E53: YOU | F53: INSUMO COZ | G53: aipim
... A69: 176 | B69: 46156 | C69: 82.03 | D69: CONDOR SUPER CENTER LTDA | E69: YOU | F69: INSUMO COZ | G69: bruschetta ecsene de onça
A70: 178 | B70: 46148 | C70: 145.5 | D70: Emily Carolini Gomes Ribeiro | E70: L1 | F70: STAFF ESPAÇO | G70: 608
A71: 178 | B71: 46148 | C71: 220 | D71: GREGORY GASPAR DE F. PROAK | E71: L1 | F71: SEGURANÇA | G71: 610
A72: 178 | B72: 46148 | C72: 210 | D72: GREGORY GASPAR DE F. PROAK | E72: L1 | F72: SEGURANÇA | G72: 611
A73: 178 | B73: 46148 | C73: 210 | D73: GREGORY GASPAR DE F. PROAK | E73: L1 | F73: SEGURANÇA | G73: 612
A74: 178 | B74: 46148 | C74: 220 | D74: GREGORY GASPAR DE F. PROAK | E74: L1 | F74: SEGURANÇA | G74: 613
A75: 176 | B75: 46159 | C75: 304.96 | D75: CONDOR SUPER CENTER LTDA | E75: YOU | F75: INSUMO COZ | G75: evento pizzas eFF01
A76: 176 | B76: 46160 | C76: 104.09 | D76: CONDOR SUPER CENTER LTDA | E76: YOU | F76: INSUMO COZ | G76: evento 20/05
A77: 178 | B77: 46148 | C77: 170 | D77: Kelli samarita de Castro | E77: L2 | F77: STAFF SERVIÇO | G77: 606
A78: 178 | B78: 46148 | C78: 178.5 | D78: Kelli samarita de Castro | E78: L2 | F78: STAFF SERVIÇO | G78: 607
A79: 176 | B79: 46162 | C79: 183.92 | D79: CONDOR SUPER CENTER LTDA | E79: YOU | F79: INSUMO COZ | G79: arbóreo
A80: 176 | B80: 46165 | C80: 172.8 | D80: CONDOR SUPER CENTER LTDA | E80: YOU | F80: INSUMO COZ | G80: bar limao hirtela
A81: 176 | B81: 46172 | C81: 253.11 | D81: CONDOR SUPER CENTER LTDA | E81: YOU | F81: INSUMO COZ | G81: evento 30/05
A82: 176 | B82: 46173 | C82: 285.75 | D82: CONDOR SUPER CENTER LTDA | E82: YOU | F82: INSUMO COZ | G82: 001
A83: 176 | B83: 46150 | C83: 1351.1 | D83: Copal Alimentos Ltda | E83: YOU | F83: INSUMO COZ | G83: evento 08 e 09/05
A84: 176 | B84: 46155 | C84: 543.5 | D84: Copal Alimentos Ltda | E84: YOU | F84: INSUMO COZ | G84: eventos 15 e 16
A85: 176 | B85: 46161 | C85: 1011.61 | D85: Copal Alimentos Ltda | E85: YOU | F85: INSUMO COZ | G85: eventos 20 a 24
A86: 176 | B86: 46163 | C86: 602.56 | D86: Copal Alimentos Ltda | E86: YOU | F86: INSUMO COZ | G86: eventos 22 e 23
A87: 176 | B87: 46172 | C87: 110.5 | D87: daniel sydorak plinta | E87: YOU | F87: INSUMO COZ | G87: 3009
A88: 176 | B88: 46147 | C88: 250 | D88: DISTRIBUIDORA PAIOL | E88: YOU | F88: INSUMO COZ | G88: gás
A89: 176 | B89: 46162 | C89: 250 | D89: DISTRIBUIDORA PAIOL | E89: YOU | F89: INSUMO COZ | G89: gás
A90: 178 | B90: 46148 | C90: 178.5 | D90: suki martins | E90: L1 | F90: STAFF FAXINA/MONTAGEM | G90: 607
A91: 176 | B91: 46148 | C91: 110.5 | D91: Dixon mejia | E91: YOU | F91: INSUMO COZ | G91: 0621
A92: 176 | B92: 46152 | C92: 144.5 | D92: Dixon mejia | E92: YOU | F92: INSUMO COZ | G92: 1008
A93: 176 | B93: 46159 | C93: 127.5 | D93: Dixon mejia | E93: YOU | F93: INSUMO COZ | G93: 1711
A94: 176 | B94: 46149 | C94: 119.78 | D94: EBAZAR.COM.BR LTDA | E94: YOU | F94: INSUMO COZ | G94: insumo cozinha
A95: 176 | B95: 46168 | C95: 67.66 | D95: EBAZAR.COM.BR LTDA | E95: YOU | F95: INSUMO COZ | G95: insumo coz
A96: 176 | B96: 46153 | C96: 315 | D96: Jeferson Fernando arceli | E96: YOU | F96: INSUMO COZ | G96: paes burguer ehotdog
A97: 176 | B97: 46160 | C97: 175 | D97: Jeferson Fernando arceli | E97: YOU | F97: INSUMO COZ | G97: paes.minihamburguer
A98: 176 | B98: 46148 | C98: 25.98 | D98: LEROY MERLIN CIA BRASILEIRA DE BRICOLAGEM | E98: YOU | F98: INSUMO COZ | G98: luvas termicas
A99: 176 | B99: 46147 | C99: 30.36 | D99: PLATINOX LOJA | E99: YOU | F99: INSUMO COZ | G99: gas macarico
A100: 176 | B100: 46146 | C100: 75 | D100: POP HOUSE | E100: YOU | F100: INSUMO COZ | G100: nozes antepastos
A101: 176 | B101: 46144 | C101: 246.93 | D101: rei do queijo | E101: YOU | F101: INSUMO COZ | G101: evento 02/05
A102: 176 | B102: 46146 | C102: 1033.89 | D102: rei do queijo | E102: YOU | F102: INSUMO COZ | G102: eventos 05 e 06
... A124: 176 | B124: 46144 | C124: 17 | D124: SENDAS DISTRIBUIDORA S/A | E124: YOU | F124: INSUMO COZ | G124: ecento 02
A125: 178 | B125: 46149 | C125: 3335.94 | D125: Gabrielle de Fatima Ribeiro cubas | E125: L1 | F125: JÁ LANÇADO | G125: 909990
A126: 176 | B126: 46144 | C126: 56.04 | D126: SENDAS DISTRIBUIDORA S/A | E126: YOU | F126: INSUMO COZ | G126: pao taxas
A127: 176 | B127: 46144 | C127: 613.9 | D127: SENDAS DISTRIBUIDORA S/A | E127: YOU | F127: INSUMO COZ | G127: evento 02
A128: 176 | B128: 46145 | C128: 181.93 | D128: SENDAS DISTRIBUIDORA S/A | E128: YOU | F128: INSUMO COZ | G128: eventos 05 e 06
A129: 176 | B129: 46145 | C129: 358.13 | D129: SENDAS DISTRIBUIDORA S/A | E129: YOU | F129: INSUMO COZ | G129: eventos 05/05
A130: 176 | B130: 46146 | C130: 652.35 | D130: SENDAS DISTRIBUIDORA S/A | E130: YOU | F130: INSUMO COZ | G130: eventos 05 e 06
A131: 178 | B131: 46149 | C131: 5315.62 | D131: Larissa Ghellere | E131: L1 | F131: JÁ LANÇADO | G131: 75001
A132: 176 | B132: 46147 | C132: 32.94 | D132: SENDAS DISTRIBUIDORA S/A | E132: YOU | F132: INSUMO COZ | G132: 001
A133: 178 | B133: 46149 | C133: 672 | D133: Talento Nexus | E133: L1 | F133: MARKETING | G133: 70510
A134: 176 | B134: 46147 | C134: 269.1 | D134: SENDAS DISTRIBUIDORA S/A | E134: YOU | F134: INSUMO COZ | G134: eventos 05 e 06
A135: 176 | B135: 46148 | C135: 178.44 | D135: SENDAS DISTRIBUIDORA S/A | E135: YOU | F135: INSUMO COZ | G135: evento dia 05 e 07
A136: 176 | B136: 46150 | C136: 68.19 | D136: SENDAS DISTRIBUIDORA S/A | E136: YOU | F136: INSUMO COZ | G136: leite milk shake
A137: 176 | B137: 46150 | C137: 296.31 | D137: SENDAS DISTRIBUIDORA S/A | E137: YOU | F137: INSUMO COZ | G137: eve tos 08 e 09
A138: 176 | B138: 46150 | C138: 505.55 | D138: SENDAS DISTRIBUIDORA S/A | E138: YOU | F138: INSUMO COZ | G138: eventos 08 e 09
A139: 176 | B139: 46151 | C139: 163.75 | D139: SENDAS DISTRIBUIDORA S/A | E139: YOU | F139: INSUMO COZ | G139: gengibre e cremede leite
A140: 176 | B140: 46151 | C140: 242.32 | D140: SENDAS DISTRIBUIDORA S/A | E140: YOU | F140: INSUMO COZ | G140: eventos 09/05
A141: 176 | B141: 46155 | C141: 506.44 | D141: SENDAS DISTRIBUIDORA S/A | E141: YOU | F141: INSUMO COZ | G141: eventos
A142: 176 | B142: 46157 | C142: 112.05 | D142: SENDAS DISTRIBUIDORA S/A | E142: YOU | F142: INSUMO COZ | G142: arboreo
A143: 176 | B143: 46158 | C143: 71.35 | D143: SENDAS DISTRIBUIDORA S/A | E143: YOU | F143: INSUMO COZ | G143: baguetes
A144: 176 | B144: 46158 | C144: 554.27 | D144: SENDAS DISTRIBUIDORA S/A | E144: YOU | F144: INSUMO COZ | G144: evento 16/05
A145: 178 | B145: 46150 | C145: 100.05 | D145: Jordana Gabriela do Sanros Carvalho | E145: L1 | F145: STAFF FAXINA/MONTAGEM | G145: rtc 03/05
... A171: 176 | B171: 46149 | C171: 68.95 | D171: Supermercado Festval | E171: YOU | F171: INSUMO COZ | G171: degustaçoes
A172: 178 | B172: 46151 | C172: 170 | D172: Kelli samarita de Castro | E172: L1 | F172: STAFF SERVIÇO | G172: 905
A173: 176 | B173: 46151 | C173: 262.98 | D173: Supermercado Festval | E173: YOU | F173: INSUMO COZ | G173: eventos 09/05
A174: 176 | B174: 46164 | C174: 264.72 | D174: Supermercado Festval | E174: YOU | F174: INSUMO COZ | G174: evento 23/05
A175: 176 | B175: 46165 | C175: 197.56 | D175: Supermercado Festval | E175: YOU | F175: INSUMO COZ | G175: antepastos
A176: 176 | B176: 46170 | C176: 70.46 | D176: Supermercado Festval | E176: YOU | F176: INSUMO COZ | G176: arboreo lombooregano e tomateseco
A177: 176 | B177: 46156 | C177: 1192.81 | D177: Trapiche Comercio de Produtos e Alimenticios Eireli | E177: YOU | F177: INSUMO COZ | G177: salmao e camarao
A178: 176 | B178: 46146 | C178: 19 | D178: EBAZAR.COM.BR LTDA | E178: YOU | F178: INSUMO LIMP | G178: esponja
A179: 176 | B179: 46156 | C179: 265.7 | D179: PINHAPEL COMERCIO DE PAPEIS LTDA | E179: YOU | F179: INSUMO SALÃO | G179: 1414
...

Sheet Cópia de GASTOS DETALHADOS
A1: PI | B1: Dt. Pagto | C1: Vlr. Pagto | D1: Fornecedor | E1: ESPAÇO | F1: SETOR | G1: NF
A2: 176 | B2: 46203 | C2: 437.74 | D2: SENDAS DISTRIBUIDORA S/A | E2: YOU | G2: degustação
A3: 176 | B3: 46203 | C3: 21.98 | D3: SACOLAO POPULAR CURITIBANO | G3: moiashi e manjericao
A4: 176 | B4: 46203 | C4: 406.11 | D4: CAMILO E TUTUMI HORTIFRUTI | G4: eventos
A5: 176 | B5: 46203 | C5: 51.22 | D5: EBAZAR.COM.BR LTDA | G5: utensilio coz
A6: 176 | B6: 46203 | C6: 1048.69 | D6: Aurora Cooperativa | G6: parmesao e manteiga
A7: 176 | B7: 46203 | C7: 72.19 | D7: SENDAS DISTRIBUIDORA S/A | G7: 1
A8: 176 | B8: 46203 | C8: 136 | D8: Thaissa cubas ribeiro dos santos | G8: 3007
A9: 176 | B9: 46203 | C9: 136 | D9: alyne carolina ropelato pacheco | G9: 3008
A10: 176 | B10: 46203 | C10: 136 | D10: Paula Kimberlly Martins Petrin | G10: 3009
A11: 176 | B11: 46203 | C11: 153 | D11: leandro lima | G11: 3009
A12: 176 | B12: 46203 | C12: 153 | D12: Hidaryane nogueira bento | G12: 3010
A13: 176 | B13: 46203 | C13: 150 | D13: Eudes Jhunior silva | G13: 300620261
A14: 176 | B14: 46202 | C14: 255 | D14: Alexis santos de Almeida | G14: taxa cozinha 27
A15: 176 | B15: 46202 | C15: 255 | D15: tathiane borcathe | G15: taxa cozinha 27
A16: 176 | B16: 46202 | C16: 160 | D16: Sônia de Jesus | G16: taxa cozinha sobremesas
A17: 176 | B17: 46202 | C17: 840 | D17: Daniel Bueno Bettega | G17: 1102
A18: 176 | B18: 46202 | C18: 1190 | D18: Eric Chien | G18: 2706
A19: 176 | B19: 46202 | C19: 2692.3 | D19: Google Inc | G19: ads20260601
A20: 176 | B20: 46202 | C20: 167.82 | D20: SENDAS DISTRIBUIDORA S/A | G20: evento 30/06
A21: 176 | B21: 46201 | C21: 247 | D21: carlos alexandre almeida de souza | G21: 2801
A22: 176 | B22: 46201 | C22: 161.5 | D22: Luiz Fernando de Jesus Rosa | G22: 280620261
A23: 176 | B23: 46201 | C23: 166.24 | D23: ZE DELIVERY APP | G23: ze dwli
A24: 176 | B24: 46201 | C24: 161.5 | D24: Fernanda Cristina Yamawaki | G24: 280620262
A25: 176 | B25: 46201 | C25: 161.5 | D25: gustavo pereira da silva | G25: 280620263
A26: 176 | B26: 46201 | C26: 161.5 | D26: luciane vieira dos santos | G26: 280620264
A27: 176 | B27: 46201 | C27: 178.5 | D27: aluir henrique | G27: 280620265
A28: 176 | B28: 46201 | C28: 178.5 | D28: Victor Sabino camargo | G28: 280620267
A29: 176 | B29: 46201 | C29: 178.5 | D29: ADRIEL DE OLIVEIRA FERNANDES | G29: 28062026
A30: 176 | B30: 46201 | C30: 153 | D30: NAIARA THAIS TOALDO PINHEIRO | G30: 2806202610
A31: 176 | B31: 46201 | C31: 161.5 | D31: Heictor Bellato Araujo | G31: 2806202611
A32: 176 | B32: 46201 | C32: 150 | D32: eduardo monteiro pinto | G32: 2806202613
A33: 176 | B33: 46201 | C33: 275 | D33: Vanessa Andreina | G33: 2806202630
A34: 176 | B34: 46201 | C34: 178 | D34: Eliana da silva moura | G34: louca cozinha
A35: 176 | B35: 46201 | C35: 178.5 | D35: Larissa Araujo | G35: 28062026
A36: 176 | B36: 46200 | C36: 153 | D36: Frederick Augusto Cezar Santos | G36: 2706
A37: 176 | B37: 46200 | C37: 153 | D37: DIOGO LUIZ ARAUJO | G37: 2702
A38: 176 | B38: 46200 | C38: 153 | D38: joel duarte | G38: 2703
A39: 176 | B39: 46200 | C39: 153 | D39: Andre Felipe Sartorelli | G39: 2705
A40: 176 | B40: 46200 | C40: 153 | D40: leandro lima | G40: 2707
A41: 176 | B41: 46200 | C41: 153 | D41: Luiz Fernando de Jesus Rosa | G41: 2708
A42: 176 | B42: 46200 | C42: 153 | D42: Agatha Pinheiro | G42: 2711
A43: 176 | B43: 46200 | C43: 140 | D43: Daniel Bueno Bettega | G43: texnixo
A44: 176 | B44: 46200 | C44: 150 | D44: Isabella Anália de Oliveira Beraldo | G44: 2711
A45: 176 | B45: 46200 | C45: 150 | D45: Alessandra Ketlyn sá silva | G45: 2712
A46: 176 | B46: 46200 | C46: 178.5 | D46: carlos alexandre almeida de souza | G46: 2713
A47: 176 | B47: 46200 | C47: 178.5 | D47: Paula Kimberlly Martins Petrin | G47: 2714
A48: 176 | B48: 46200 | C48: 178.5 | D48: Fabio Bueno Skalecki | G48: 2715
A49: 176 | B49: 46200 | C49: 178.5 | D49: ADRIEL DE OLIVEIRA FERNANDES | G49: 2716
A50: 176 | B50: 46200 | C50: 161.5 | D50: Juliana Cordova | G50: 2717
A51: 176 | B51: 46200 | C51: 161.5 | D51: Kelli samarita de Castro | G51: 2718
A52: 176 | B52: 46200 | C52: 178.5 | D52: aluir henrique | G52: 2718
A53: 176 | B53: 46200 | C53: 150 | D53: Thaissa cubas ribeiro dos santos | G53: 2719
A54: 176 | B54: 46200 | C54: 170 | D54: alyne carolina ropelato pacheco | G54: 2721
A55: 176 | B55: 46200 | C55: 47.91 | D55: Auto Posto Agua Verde | G55: combustivel
A56: 176 | B56: 46200 | C56: 202.19 | D56: rei do queijo | G56: creme de leitr
A57: 176 | B57: 46200 | C57: 256.57 | D57: SENDAS DISTRIBUIDORA S/A | G57: evento 27
A58: 176 | B58: 46200 | C58: 27.77 | D58: SACOLAO POPULAR CURITIBANO | G58: limao
A59: 176 | B59: 46200 | C59: 170 | D59: juliana galerani | G59: 2721
A60: 176 | B60: 46200 | C60: 70.52 | D60: SENDAS DISTRIBUIDORA S/A | G60: comida taxas
A61: 176 | B61: 46200 | C61: 158.71 | D61: SENDAS DISTRIBUIDORA S/A | G61: muçarela
A62: 176 | B62: 46200 | C62: 422.87 | D62: CARREFOUR COMERCIO E INDUSTRIA LTDA | G62: insumo bar
A63: 176 | B63: 46200 | C63: 127.5 | D63: Vitoria de Oliveira Coelho | G63: 2722
A64: 176 | B64: 46200 | C64: 187 | D64: Paula Kimberlly Martins Petrin | G64: 2723
A65: 176 | B65: 46200 | C65: 187 | D65: Fabio Bueno Skalecki | G65: 2724
A66: 176 | B66: 46200 | C66: 170 | D66: Kelli samarita de Castro | G66: 2725
A67: 176 | B67: 46200 | C67: 170 | D67: leandro lima | G67: 2726
A68: 176 | B68: 46200 | C68: 170 | D68: joel duarte | G68: 2727
A69: 176 | B69: 46200 | C69: 41.76 | D69: Kelli samarita de Castro | G69: 2728
A70: 176 | B70: 46200 | C70: 333.66 | D70: ZE DELIVERY APP | G70: gelo
A71: 176 | B71: 46200 | C71: 17 | D71: Vitoria de Oliveira Coelho | G71: 2729
A72: 176 | B72: 46199 | C72: 295.5 | D72: SENDAS DISTRIBUIDORA S/A | G72: bar
A73: 176 | B73: 46199 | C73: 392.08 | D73: AÇOUGUE TIROLEZA | G73: musculo nuggts
A74: 176 | B74: 46199 | C74: 80.3 | D74: WMS SUPERMERCADOS DO BRASIL LTDA (CARREFOUR) | G74: bar
A75: 176 | B75: 46199 | C75: 11.99 | D75: SACOLAO POPULAR CURITIBANO | G75: moyashi
A76: 176 | B76: 46199 | C76: 71.68 | D76: UBER DO BRASIL | G76: lalamoe
A77: 176 | B77: 46199 | C77: 513.9 | D77: EMPRESA DE AGUAS PE DA SERRA LTDA | G77: insumo bar
A78: 176 | B78: 46199 | C78: 2159.54 | D78: Governo Federal / Imp. Ret. Forn / PIS-Cofins-CSLL | G78: DAS 7/12
A79: 176 | B79: 46199 | C79: 1090.53 | D79: Governo Federal / Imp. Ret. Venda / Cofins | G79: SIMPLES NACIONAL
A80: 176 | B80: 46199 | C80: 114.35 | D80: Governo Federal / Imp. Ret. Func./ INSS | G80: divida ativa
A81: 176 | B81: 46199 | C81: 527.19 | D81: SENDAS DISTRIBUIDORA S/A | G81: bar coca guardanapo
A82: 176 | B82: 46199 | C82: 542.81 | D82: ZE DELIVERY APP | G82: insumo bar
A83: 176 | B83: 46199 | C83: 225 | D83: Alexis santos de Almeida | G83: taxa cozinha 26/06
... A89: 176 | B89: 46198 | C89: 218.78 | D89: AÇOUGUE TIROLEZA | G89: eventos 26 e 27
A90: 176 | B90: 46197 | C90: 445.45 | D90: SENDAS DISTRIBUIDORA S/A | G90: 1
A91: 176 | B91: 46197 | C91: 490.76 | D91: AÇOUGUE TIROLEZA | G91: mini burguer empanadas chilli
A92: 176 | B92: 46197 | C92: 170 | D92: Thaissa cubas ribeiro dos santos | G92: 2403
A93: 176 | B93: 46197 | C93: 170 | D93: Paula Kimberlly Martins Petrin | G93: 2404
A94: 176 | B94: 46197 | C94: 136 | D94: leandro lima | G94: 2405
A95: 176 | B95: 46197 | C95: 136 | D95: Victor Sabino camargo | G95: 2406
A96: 176 | B96: 46197 | C96: 136 | D96: ADRIEL DE OLIVEIRA FERNANDES | G96: 2407
A97: 176 | B97: 46197 | C97: 119 | D97: alyne carolina ropelato pacheco | G97: 2408
A98: 176 | B98: 46197 | C98: 138.9 | D98: EBAZAR.COM.BR LTDA | G98: carregador notebook cozinha
A99: 176 | B99: 46197 | C99: 190 | D99: Alexis santos de Almeida | G99: evento 24
A100: 176 | B100: 46197 | C100: 160 | D100: tathiane borcathe | G100: evento 24
A101: 176 | B101: 46197 | C101: 100 | D101: Arthur Antunes de Sá | G101: louca adicional domingo
A102: 176 | B102: 46197 | C102: 136 | D102: gustavo gabryel de souza roberto | G102: 2409
A103: 176 | B103: 46196 | C103: 32.36 | D103: rei do queijo | G103: calabresa pizza
A104: 176 | B104: 46196 | C104: 23.15 | D104: SACOLAO POPULAR CURITIBANO | G104: abacate
A105: 176 | B105: 46196 | C105: 558.68 | D105: SENDAS DISTRIBUIDORA S/A | G105: eventos 24
...
